{
  "ipcMode": null,
  "executionRoleArn": null,
  "containerDefinitions": [
    {
      "dnsSearchDomains": null,
      "environmentFiles": null,
      "logConfiguration": null,
      "entryPoint": [],
      "portMappings": [
        {
          "hostPort": 3000,
          "protocol": "tcp",
          "containerPort": 3000
        }
      ],
      "command": [],
      "linuxParameters": null,
      "cpu": 0,
      "environment": [],
      "resourceRequirements": null,
      "ulimits": null,
      "dnsServers": null,
      "mountPoints": [],
      "workingDirectory": null,
      "secrets": null,
      "dockerSecurityOptions": null,
      "memory": null,
      "memoryReservation": null,
      "volumesFrom": [],
      "stopTimeout": null,
      "image": "081493724379.dkr.ecr.eu-central-1.amazonaws.com/my-cont-repo:latest",
      "startTimeout": null,
      "firelensConfiguration": null,
      "dependsOn": null,
      "disableNetworking": null,
      "interactive": null,
      "healthCheck": null,
      "essential": true,
      "links": null,
      "hostname": null,
      "extraHosts": null,
      "pseudoTerminal": null,
      "user": null,
      "readonlyRootFilesystem": null,
      "dockerLabels": null,
      "systemControls": null,
      "privileged": null,
      "name": "node-server2"
    }
  ],
  "placementConstraints": [],
  "memory": "3072",
  "taskRoleArn": null,
  "compatibilities": [
    "EXTERNAL",
    "EC2"
  ],
  "taskDefinitionArn": "arn:aws:ecs:eu-central-1:081493724379:task-definition/MyTaskDefinition2:1",
  "family": "MyTaskDefinition2",
  "requiresAttributes": [
    {
      "targetId": null,
      "targetType": null,
      "value": null,
      "name": "com.amazonaws.ecs.capability.ecr-auth"
    }
  ],
  "pidMode": null,
  "requiresCompatibilities": [
    "EC2"
  ],
  "networkMode": "bridge",
  "runtimePlatform": null,
  "cpu": "1024",
  "revision": 1,
  "status": "ACTIVE",
  "inferenceAccelerators": null,
  "proxyConfiguration": null,
  "volumes": []
}
